eldritha/__init__.py
eldritha/ext/__init__.py
eldritha/ext/exceptions.py
eldritha/orm/__init__.py
eldritha/orm/engine.py
eldritha/orm/session.py
eldritha/orm/tables.py
eldritha/redis/__init__.py
eldritha/redis/redis_client.py
nyria_eldritha-1.1.1.dist-info/LICENSE
nyria_eldritha-1.1.1.dist-info/METADATA
nyria_eldritha-1.1.1.dist-info/WHEEL
nyria_eldritha-1.1.1.dist-info/top_level.txt
nyria_eldritha-1.1.1.dist-info/RECORD
